[{"arguments":["clang","-Wno-documentation-unknown-command","-Wno-unknown-warning-option","-Wno-unknown-pragmas","-nostdinc","-nostdinc++","-DQT_QML_DEBUG","-g","-std=gnu++17","-fdiagnostics-color=always","-fsyntax-only","-m64","--target=x86_64-w64-mingw32","-DMINGW_HAS_SECURE_API","-DPICE_DLL_LIBRARY","-DQT_CORE_LIB","-DRIFFA_EXPORTS","-DUNICODE","-DWIN32","-DWIN64","-D_ENABLE_EXTENDED_ALIGNED_STORAGE","-D_UNICODE","-D_WIN64","-Dpice_dll_EXPORTS","-DQ_CREATOR_RUN","-DQT_ANNOTATE_FUNCTION(x)=__attribute__((annotate(#x)))","-IG:\\Qt\\Tools\\QtCreator\\share\\qtcreator\\cplusplus\\wrappedMingwHeaders","-IG:\\Qt\\Tools\\QtCreator\\share\\qtcreator\\cplusplus\\wrappedQtHeaders","-IG:\\Qt\\Tools\\QtCreator\\share\\qtcreator\\cplusplus\\wrappedQtHeaders\\QtCore","-IG:\\Qt\\learning\\pice_dll\\build\\Desktop_Qt_6_7_0_MinGW_64_bit-Debug\\pice_dll_autogen\\include","-IG:\\Qt\\learning\\pice_dll\\include","-isystem","G:\\Qt\\6.7.0\\mingw_64\\include\\QtCore","-isystem","G:\\Qt\\6.7.0\\mingw_64\\include","-isystem","G:\\Qt\\6.7.0\\mingw_64\\mkspecs\\win32-g++","-isystem","G:\\Qt\\Tools\\mingw1120_64\\lib\\gcc\\x86_64-w64-mingw32\\11.2.0\\include\\c++","-isystem","G:\\Qt\\Tools\\mingw1120_64\\lib\\gcc\\x86_64-w64-mingw32\\11.2.0\\include\\c++\\x86_64-w64-mingw32","-isystem","G:\\Qt\\Tools\\mingw1120_64\\lib\\gcc\\x86_64-w64-mingw32\\11.2.0\\include\\c++\\backward","-isystem","G:\\Qt\\Tools\\QtCreator\\bin\\clang\\lib\\clang\\18\\include","-isystem","G:\\Qt\\Tools\\mingw1120_64\\x86_64-w64-mingw32\\include","-fmessage-length=0","-fdiagnostics-show-note-include-stack","-fretain-comments-from-system-headers","-fmacro-backtrace-limit=0","-ferror-limit=1000","-x","c++","G:\\Qt\\learning\\pice_dll\\pice_dll.cpp"],"directory":"G:/Qt/learning/pice_dll/build/Desktop_Qt_6_7_0_MinGW_64_bit-Debug/.qtc_clangd","file":"G:/Qt/learning/pice_dll/pice_dll.cpp"},{"arguments":["clang","-Wno-documentation-unknown-command","-Wno-unknown-warning-option","-Wno-unknown-pragmas","-nostdinc","-nostdinc++","-DQT_QML_DEBUG","-g","-std=gnu++17","-fdiagnostics-color=always","-fsyntax-only","-m64","--target=x86_64-w64-mingw32","-DMINGW_HAS_SECURE_API","-DPICE_DLL_LIBRARY","-DQT_CORE_LIB","-DRIFFA_EXPORTS","-DUNICODE","-DWIN32","-DWIN64","-D_ENABLE_EXTENDED_ALIGNED_STORAGE","-D_UNICODE","-D_WIN64","-Dpice_dll_EXPORTS","-DQ_CREATOR_RUN","-DQT_ANNOTATE_FUNCTION(x)=__attribute__((annotate(#x)))","-IG:\\Qt\\Tools\\QtCreator\\share\\qtcreator\\cplusplus\\wrappedMingwHeaders","-IG:\\Qt\\Tools\\QtCreator\\share\\qtcreator\\cplusplus\\wrappedQtHeaders","-IG:\\Qt\\Tools\\QtCreator\\share\\qtcreator\\cplusplus\\wrappedQtHeaders\\QtCore","-IG:\\Qt\\learning\\pice_dll\\build\\Desktop_Qt_6_7_0_MinGW_64_bit-Debug\\pice_dll_autogen\\include","-IG:\\Qt\\learning\\pice_dll\\include","-isystem","G:\\Qt\\6.7.0\\mingw_64\\include\\QtCore","-isystem","G:\\Qt\\6.7.0\\mingw_64\\include","-isystem","G:\\Qt\\6.7.0\\mingw_64\\mkspecs\\win32-g++","-isystem","G:\\Qt\\Tools\\mingw1120_64\\lib\\gcc\\x86_64-w64-mingw32\\11.2.0\\include\\c++","-isystem","G:\\Qt\\Tools\\mingw1120_64\\lib\\gcc\\x86_64-w64-mingw32\\11.2.0\\include\\c++\\x86_64-w64-mingw32","-isystem","G:\\Qt\\Tools\\mingw1120_64\\lib\\gcc\\x86_64-w64-mingw32\\11.2.0\\include\\c++\\backward","-isystem","G:\\Qt\\Tools\\QtCreator\\bin\\clang\\lib\\clang\\18\\include","-isystem","G:\\Qt\\Tools\\mingw1120_64\\x86_64-w64-mingw32\\include","-fmessage-length=0","-fdiagnostics-show-note-include-stack","-fretain-comments-from-system-headers","-fmacro-backtrace-limit=0","-ferror-limit=1000","-x","c++","G:\\Qt\\learning\\pice_dll\\riffa.cpp"],"directory":"G:/Qt/learning/pice_dll/build/Desktop_Qt_6_7_0_MinGW_64_bit-Debug/.qtc_clangd","file":"G:/Qt/learning/pice_dll/riffa.cpp"},{"arguments":["clang","-Wno-documentation-unknown-command","-Wno-unknown-warning-option","-Wno-unknown-pragmas","-nostdinc","-nostdinc++","-DQT_QML_DEBUG","-g","-std=gnu++17","-fdiagnostics-color=always","-fsyntax-only","-m64","--target=x86_64-w64-mingw32","-DMINGW_HAS_SECURE_API","-DPICE_DLL_LIBRARY","-DQT_CORE_LIB","-DRIFFA_EXPORTS","-DUNICODE","-DWIN32","-DWIN64","-D_ENABLE_EXTENDED_ALIGNED_STORAGE","-D_UNICODE","-D_WIN64","-Dpice_dll_EXPORTS","-DQ_CREATOR_RUN","-DQT_ANNOTATE_FUNCTION(x)=__attribute__((annotate(#x)))","-IG:\\Qt\\Tools\\QtCreator\\share\\qtcreator\\cplusplus\\wrappedMingwHeaders","-IG:\\Qt\\Tools\\QtCreator\\share\\qtcreator\\cplusplus\\wrappedQtHeaders","-IG:\\Qt\\Tools\\QtCreator\\share\\qtcreator\\cplusplus\\wrappedQtHeaders\\QtCore","-IG:\\Qt\\learning\\pice_dll\\build\\Desktop_Qt_6_7_0_MinGW_64_bit-Debug\\pice_dll_autogen\\include","-IG:\\Qt\\learning\\pice_dll\\include","-isystem","G:\\Qt\\6.7.0\\mingw_64\\include\\QtCore","-isystem","G:\\Qt\\6.7.0\\mingw_64\\include","-isystem","G:\\Qt\\6.7.0\\mingw_64\\mkspecs\\win32-g++","-isystem","G:\\Qt\\Tools\\mingw1120_64\\lib\\gcc\\x86_64-w64-mingw32\\11.2.0\\include\\c++","-isystem","G:\\Qt\\Tools\\mingw1120_64\\lib\\gcc\\x86_64-w64-mingw32\\11.2.0\\include\\c++\\x86_64-w64-mingw32","-isystem","G:\\Qt\\Tools\\mingw1120_64\\lib\\gcc\\x86_64-w64-mingw32\\11.2.0\\include\\c++\\backward","-isystem","G:\\Qt\\Tools\\QtCreator\\bin\\clang\\lib\\clang\\18\\include","-isystem","G:\\Qt\\Tools\\mingw1120_64\\x86_64-w64-mingw32\\include","-fmessage-length=0","-fdiagnostics-show-note-include-stack","-fretain-comments-from-system-headers","-fmacro-backtrace-limit=0","-ferror-limit=1000","-x","c++-header","G:\\Qt\\learning\\pice_dll\\pice_dll_global.h"],"directory":"G:/Qt/learning/pice_dll/build/Desktop_Qt_6_7_0_MinGW_64_bit-Debug/.qtc_clangd","file":"G:/Qt/learning/pice_dll/pice_dll_global.h"},{"arguments":["clang","-Wno-documentation-unknown-command","-Wno-unknown-warning-option","-Wno-unknown-pragmas","-nostdinc","-nostdinc++","-DQT_QML_DEBUG","-g","-std=gnu++17","-fdiagnostics-color=always","-fsyntax-only","-m64","--target=x86_64-w64-mingw32","-DMINGW_HAS_SECURE_API","-DPICE_DLL_LIBRARY","-DQT_CORE_LIB","-DRIFFA_EXPORTS","-DUNICODE","-DWIN32","-DWIN64","-D_ENABLE_EXTENDED_ALIGNED_STORAGE","-D_UNICODE","-D_WIN64","-Dpice_dll_EXPORTS","-DQ_CREATOR_RUN","-DQT_ANNOTATE_FUNCTION(x)=__attribute__((annotate(#x)))","-IG:\\Qt\\Tools\\QtCreator\\share\\qtcreator\\cplusplus\\wrappedMingwHeaders","-IG:\\Qt\\Tools\\QtCreator\\share\\qtcreator\\cplusplus\\wrappedQtHeaders","-IG:\\Qt\\Tools\\QtCreator\\share\\qtcreator\\cplusplus\\wrappedQtHeaders\\QtCore","-IG:\\Qt\\learning\\pice_dll\\build\\Desktop_Qt_6_7_0_MinGW_64_bit-Debug\\pice_dll_autogen\\include","-IG:\\Qt\\learning\\pice_dll\\include","-isystem","G:\\Qt\\6.7.0\\mingw_64\\include\\QtCore","-isystem","G:\\Qt\\6.7.0\\mingw_64\\include","-isystem","G:\\Qt\\6.7.0\\mingw_64\\mkspecs\\win32-g++","-isystem","G:\\Qt\\Tools\\mingw1120_64\\lib\\gcc\\x86_64-w64-mingw32\\11.2.0\\include\\c++","-isystem","G:\\Qt\\Tools\\mingw1120_64\\lib\\gcc\\x86_64-w64-mingw32\\11.2.0\\include\\c++\\x86_64-w64-mingw32","-isystem","G:\\Qt\\Tools\\mingw1120_64\\lib\\gcc\\x86_64-w64-mingw32\\11.2.0\\include\\c++\\backward","-isystem","G:\\Qt\\Tools\\QtCreator\\bin\\clang\\lib\\clang\\18\\include","-isystem","G:\\Qt\\Tools\\mingw1120_64\\x86_64-w64-mingw32\\include","-fmessage-length=0","-fdiagnostics-show-note-include-stack","-fretain-comments-from-system-headers","-fmacro-backtrace-limit=0","-ferror-limit=1000","-x","c++-header","G:\\Qt\\learning\\pice_dll\\pice_dll.h"],"directory":"G:/Qt/learning/pice_dll/build/Desktop_Qt_6_7_0_MinGW_64_bit-Debug/.qtc_clangd","file":"G:/Qt/learning/pice_dll/pice_dll.h"},{"arguments":["clang","-Wno-documentation-unknown-command","-Wno-unknown-warning-option","-Wno-unknown-pragmas","-nostdinc","-nostdinc++","-DQT_QML_DEBUG","-g","-std=gnu++17","-fdiagnostics-color=always","-fsyntax-only","-m64","--target=x86_64-w64-mingw32","-DMINGW_HAS_SECURE_API","-DPICE_DLL_LIBRARY","-DQT_CORE_LIB","-DRIFFA_EXPORTS","-DUNICODE","-DWIN32","-DWIN64","-D_ENABLE_EXTENDED_ALIGNED_STORAGE","-D_UNICODE","-D_WIN64","-Dpice_dll_EXPORTS","-DQ_CREATOR_RUN","-DQT_ANNOTATE_FUNCTION(x)=__attribute__((annotate(#x)))","-IG:\\Qt\\Tools\\QtCreator\\share\\qtcreator\\cplusplus\\wrappedMingwHeaders","-IG:\\Qt\\Tools\\QtCreator\\share\\qtcreator\\cplusplus\\wrappedQtHeaders","-IG:\\Qt\\Tools\\QtCreator\\share\\qtcreator\\cplusplus\\wrappedQtHeaders\\QtCore","-IG:\\Qt\\learning\\pice_dll\\build\\Desktop_Qt_6_7_0_MinGW_64_bit-Debug\\pice_dll_autogen\\include","-IG:\\Qt\\learning\\pice_dll\\include","-isystem","G:\\Qt\\6.7.0\\mingw_64\\include\\QtCore","-isystem","G:\\Qt\\6.7.0\\mingw_64\\include","-isystem","G:\\Qt\\6.7.0\\mingw_64\\mkspecs\\win32-g++","-isystem","G:\\Qt\\Tools\\mingw1120_64\\lib\\gcc\\x86_64-w64-mingw32\\11.2.0\\include\\c++","-isystem","G:\\Qt\\Tools\\mingw1120_64\\lib\\gcc\\x86_64-w64-mingw32\\11.2.0\\include\\c++\\x86_64-w64-mingw32","-isystem","G:\\Qt\\Tools\\mingw1120_64\\lib\\gcc\\x86_64-w64-mingw32\\11.2.0\\include\\c++\\backward","-isystem","G:\\Qt\\Tools\\QtCreator\\bin\\clang\\lib\\clang\\18\\include","-isystem","G:\\Qt\\Tools\\mingw1120_64\\x86_64-w64-mingw32\\include","-fmessage-length=0","-fdiagnostics-show-note-include-stack","-fretain-comments-from-system-headers","-fmacro-backtrace-limit=0","-ferror-limit=1000","-x","c++-header","G:\\Qt\\learning\\pice_dll\\riffa.h"],"directory":"G:/Qt/learning/pice_dll/build/Desktop_Qt_6_7_0_MinGW_64_bit-Debug/.qtc_clangd","file":"G:/Qt/learning/pice_dll/riffa.h"},{"arguments":["clang","-Wno-documentation-unknown-command","-Wno-unknown-warning-option","-Wno-unknown-pragmas","-nostdinc","-nostdinc++","-DQT_QML_DEBUG","-g","-std=gnu++17","-fdiagnostics-color=always","-fsyntax-only","-m64","--target=x86_64-w64-mingw32","-DMINGW_HAS_SECURE_API","-DPICE_DLL_LIBRARY","-DQT_CORE_LIB","-DRIFFA_EXPORTS","-DUNICODE","-DWIN32","-DWIN64","-D_ENABLE_EXTENDED_ALIGNED_STORAGE","-D_UNICODE","-D_WIN64","-Dpice_dll_EXPORTS","-DQ_CREATOR_RUN","-DQT_ANNOTATE_FUNCTION(x)=__attribute__((annotate(#x)))","-IG:\\Qt\\Tools\\QtCreator\\share\\qtcreator\\cplusplus\\wrappedMingwHeaders","-IG:\\Qt\\Tools\\QtCreator\\share\\qtcreator\\cplusplus\\wrappedQtHeaders","-IG:\\Qt\\Tools\\QtCreator\\share\\qtcreator\\cplusplus\\wrappedQtHeaders\\QtCore","-IG:\\Qt\\learning\\pice_dll\\build\\Desktop_Qt_6_7_0_MinGW_64_bit-Debug\\pice_dll_autogen\\include","-IG:\\Qt\\learning\\pice_dll\\include","-isystem","G:\\Qt\\6.7.0\\mingw_64\\include\\QtCore","-isystem","G:\\Qt\\6.7.0\\mingw_64\\include","-isystem","G:\\Qt\\6.7.0\\mingw_64\\mkspecs\\win32-g++","-isystem","G:\\Qt\\Tools\\mingw1120_64\\lib\\gcc\\x86_64-w64-mingw32\\11.2.0\\include\\c++","-isystem","G:\\Qt\\Tools\\mingw1120_64\\lib\\gcc\\x86_64-w64-mingw32\\11.2.0\\include\\c++\\x86_64-w64-mingw32","-isystem","G:\\Qt\\Tools\\mingw1120_64\\lib\\gcc\\x86_64-w64-mingw32\\11.2.0\\include\\c++\\backward","-isystem","G:\\Qt\\Tools\\QtCreator\\bin\\clang\\lib\\clang\\18\\include","-isystem","G:\\Qt\\Tools\\mingw1120_64\\x86_64-w64-mingw32\\include","-fmessage-length=0","-fdiagnostics-show-note-include-stack","-fretain-comments-from-system-headers","-fmacro-backtrace-limit=0","-ferror-limit=1000","-x","c++-header","G:\\Qt\\learning\\pice_dll\\riffa_driver.h"],"directory":"G:/Qt/learning/pice_dll/build/Desktop_Qt_6_7_0_MinGW_64_bit-Debug/.qtc_clangd","file":"G:/Qt/learning/pice_dll/riffa_driver.h"}]